{
    "Tests": { 
            {
                 "id": 0,
                "block": 1,
                "name": "Test 1 ",
                "pictureLink": "https://cdn.pixabay.com/photo/2014/09/20/20/24/serpentine-454249_960_720.jpg"
            },
            {
                "id": 1,
                "block": 2,
                "name": "Test 2",
                "pictureLink": "https://cdn.pixabay.com/photo/2014/09/20/20/24/serpentine-454249_960_720.jpg"
            },
            {
                "id": 2,
                "block": 3,
                "name": "Test 3",
                "pictureLink": "https://cdn.pixabay.com/photo/2014/09/20/20/24/serpentine-454249_960_720.jpg"
            },
            {
                "id": 3,
                "block": 4,
                "name": "Test 4",
                "pictureLink": "https://cdn.pixabay.com/photo/2014/09/20/20/24/serpentine-454249_960_720.jpg"
            },
            {
                "block": 5,
                "name": "Test 5",
                "pictureLink": "https://cdn.pixabay.com/photo/2014/09/20/20/24/serpentine-454249_960_720.jpg"
            },
            {
                "block": 6,
                "name": "Test 6",
                "pictureLink": "https://cdn.pixabay.com/photo/2014/09/20/20/24/serpentine-454249_960_720.jpg"
            },
            {
                "block": 7,
                "name": "Test 7",
                "pictureLink": "https://cdn.pixabay.com/photo/2014/09/20/20/24/serpentine-454249_960_720.jpg"
            },
            {
                "block": 8,
                "name": "Test 8",
                "pictureLink": "https://cdn.pixabay.com/photo/2014/09/20/20/24/serpentine-454249_960_720.jpg"
            }
}
 
    "AllTests": {
        "data": [
            {   "id": 0,
                "block": 1,
                "name": "Test 1 ",
                "pictureLink": "https://cdn.pixabay.com/photo/2014/09/20/20/24/serpentine-454249_960_720.jpg"
            },
            {
                "id": 1,
                "block": 2,
                "name": "Test 2",
                "pictureLink": "https://cdn.pixabay.com/photo/2014/09/20/20/24/serpentine-454249_960_720.jpg"
            },
            {
                "id": 2,
                "block": 3,
                "name": "Test 3",
                "pictureLink": "https://cdn.pixabay.com/photo/2014/09/20/20/24/serpentine-454249_960_720.jpg"
            },
            {
                "id": 3,
                "block": 4,
                "name": "Test 4",
                "pictureLink": "https://cdn.pixabay.com/photo/2014/09/20/20/24/serpentine-454249_960_720.jpg"
            },
            {
                "block": 5,
                "name": "Test 5",
                "pictureLink": "https://cdn.pixabay.com/photo/2014/09/20/20/24/serpentine-454249_960_720.jpg"
            },
            {
                "block": 6,
                "name": "Test 6",
                "pictureLink": "https://cdn.pixabay.com/photo/2014/09/20/20/24/serpentine-454249_960_720.jpg"
            },
            {
                "block": 7,
                "name": "Test 7",
                "pictureLink": "https://cdn.pixabay.com/photo/2014/09/20/20/24/serpentine-454249_960_720.jpg"
            },
            {
                "block": 8,
                "name": "Test 8",
                "pictureLink": "https://cdn.pixabay.com/photo/2014/09/20/20/24/serpentine-454249_960_720.jpg"
            }
        ],
        "status": "",
        "success": true
    },
    "Test": {
        "data": {
            "block": 1,
            "name": "Test 1 Pulled from database. ",
            "questions": [
                {
                    "values": "Question 2",
                    "pictureLink": "https://cdn.pixabay.com/photo/2018/02/05/23/05/death-valley-3133502_960_720.jpg",
                    "answer": true
                },
                {
                    "values": "Question 5",
                    "pictureLink": "https://cdn.pixabay.com/photo/2018/02/05/23/05/death-valley-3133502_960_720.jpg",
                    "answer": true
                },
                {
                    "values": "Question 6",
                    "pictureLink": "https://cdn.pixabay.com/photo/2018/02/05/23/05/death-valley-3133502_960_720.jpg",
                    "answer": true
                },
                {
                    "values": "Question 3 ",
                    "pictureLink": "https://cdn.pixabay.com/photo/2018/02/05/23/05/death-valley-3133502_960_720.jpg",
                    "answer": true
                },
                {
                    "values": "Question 9",
                    "pictureLink": "https://cdn.pixabay.com/photo/2018/02/05/23/05/death-valley-3133502_960_720.jpg",
                    "answer": true
                }
            ],
            "exercise_Six": [
                {
                    "values": "Variant 5",
                    "pictureLink": "link",
                    "answer": 5
                }
            ],
            "exercise_Seven": [
                {
                    "values": "Variant 1",
                    "pictureLink": "link",
                    "answer": 1
                }
            ],
            "exercise_Eighth": [
                {
                    "values": "Variant 3",
                    "pictureLink": "link",
                    "answer": 3
                }
            ],
            "exercise_Nine": [
                {
                    "values": "Variant 5",
                    "pictureLink": "link",
                    "answer": 5
                }
            ],
            "exercise_Ten": [
                {
                    "values": "Variant 1",
                    "pictureLink": "link",
                    "answer": 1
                }
            ]
        },
        "status": "",
        "success": true
    }
}
